fastapi_auth_audit/__init__.py
fastapi_auth_audit/audit.py
fastapi_auth_audit/config.py
fastapi_auth_audit/database.py
fastapi_auth_audit/exceptions.py
fastapi_auth_audit/models.py
fastapi_auth_audit/permission.py
fastapi_auth_audit-0.1.0.dist-info/METADATA
fastapi_auth_audit-0.1.0.dist-info/WHEEL
fastapi_auth_audit-0.1.0.dist-info/RECORD
